forgeformat/__init__.py
forgeformat/cli.py
forge_format-1.1.0.dist-info/LICENSE
forge_format-1.1.0.dist-info/METADATA
forge_format-1.1.0.dist-info/WHEEL
forge_format-1.1.0.dist-info/entry_points.txt
forge_format-1.1.0.dist-info/RECORD
